{
  "name": "Lead Nurturing Sequence",
  "nodes": [
    {
      "parameters": {
        "httpMethod": "POST",
        "path": "lead-nurturing",
        "responseMode": "responseNode",
        "options": {}
      },
      "id": "webhook-node",
      "name": "Webhook - New Lead",
      "type": "n8n-nodes-base.webhook",
      "typeVersion": 1,
      "position": [250, 300],
      "webhookId": "lead-nurturing"
    },
    {
      "parameters": {
        "respondWith": "json",
        "responseBody": "={{ { \"success\": true, \"message\": \"Lead received\", \"leadId\": $json.contact_id } }}"
      },
      "id": "respond-node",
      "name": "Respond to Webhook",
      "type": "n8n-nodes-base.respondToWebhook",
      "typeVersion": 1,
      "position": [1050, 300]
    },
    {
      "parameters": {
        "conditions": {
          "string": [
            {
              "value1": "={{ $json.source }}",
              "operation": "equals",
              "value2": "website"
            }
          ]
        }
      },
      "id": "if-node",
      "name": "Check Lead Source",
      "type": "n8n-nodes-base.if",
      "typeVersion": 1,
      "position": [450, 300]
    },
    {
      "parameters": {
        "amount": 5,
        "unit": "minutes"
      },
      "id": "wait-node-1",
      "name": "Wait 5 Minutes",
      "type": "n8n-nodes-base.wait",
      "typeVersion": 1,
      "position": [650, 200]
    },
    {
      "parameters": {
        "url": "http://localhost:3000/api/messages/send-direct",
        "method": "POST",
        "sendBody": true,
        "specifyBody": "json",
        "jsonBody": "={{ { \"phone_number\": $json.phone_number, \"message\": \"Hi \" + $json.name + \"! 👋 Thanks for your interest. How can we help you today?\", \"contact_id\": $json.contact_id } }}",
        "options": {}
      },
      "id": "send-message-1",
      "name": "Send Welcome Message",
      "type": "n8n-nodes-base.httpRequest",
      "typeVersion": 4.2,
      "position": [850, 200]
    }
  ],
  "connections": {
    "Webhook - New Lead": {
      "main": [
        [
          {
            "node": "Check Lead Source",
            "type": "main",
            "index": 0
          }
        ]
      ]
    },
    "Check Lead Source": {
      "main": [
        [
          {
            "node": "Wait 5 Minutes",
            "type": "main",
            "index": 0
          }
        ],
        [
          {
            "node": "Respond to Webhook",
            "type": "main",
            "index": 0
          }
        ]
      ]
    },
    "Wait 5 Minutes": {
      "main": [
        [
          {
            "node": "Send Welcome Message",
            "type": "main",
            "index": 0
          }
        ]
      ]
    },
    "Send Welcome Message": {
      "main": [
        [
          {
            "node": "Respond to Webhook",
            "type": "main",
            "index": 0
          }
        ]
      ]
    }
  },
  "active": false,
  "settings": {},
  "versionId": "1",
  "id": "lead-nurturing-sequence",
  "meta": {
    "instanceId": "local"
  },
  "tags": []
}
